gramep-1.2.1.dist-info/METADATA
gramep-1.2.1.dist-info/WHEEL
gramep-1.2.1.dist-info/entry_points.txt
gramep/kmers_utils.py
gramep/mutations.py
gramep/messages.py
gramep/graphics.py
gramep/cli.py
gramep/helpers.py
gramep/classify_utils.py
gramep/grid_search.py
gramep/analysis.py
gramep/__init__.py
gramep/data_io.py
gramep/config.py
gramep/utilrs.cpython-312-x86_64-linux-gnu.so
gramep-1.2.1.dist-info/RECORD
