Metadata-Version: 2.3
Name: gramep
Version: 1.2.1
Classifier: Programming Language :: Rust
Classifier: Topic :: Scientific/Engineering :: Bio-Informatics
Classifier: Topic :: Scientific/Engineering :: Artificial Intelligence
Classifier: Natural Language :: English
Classifier: Environment :: Console
Classifier: Development Status :: 5 - Production/Stable
Classifier: Intended Audience :: Science/Research
Classifier: License :: OSI Approved :: MIT License
Classifier: Programming Language :: Python :: 3.12
Requires-Dist: rich >=13.7.1
Requires-Dist: typer >=0.12.3
Requires-Dist: biopython >=1.83
Requires-Dist: pandas >=2.2.2
Requires-Dist: gffpandas >=1.2.0
Requires-Dist: joblib >=1.4.2
Requires-Dist: joblib-progress >=1.0.5
Requires-Dist: matplotlib >=3.9.0
Requires-Dist: upsetplot >=0.9.0
Requires-Dist: scikit-learn >=1.5.1
Requires-Dist: seaborn >=0.13.2
Requires-Dist: thefuzz >=0.22.1
Requires-Dist: maturin >=1.5.1 ; extra == 'dev'
Requires-Dist: pytest >=8.3.2 ; extra == 'dev'
Requires-Dist: pytest-cov >=5.0.0 ; extra == 'dev'
Requires-Dist: taskipy >=1.13.0 ; extra == 'dev'
Requires-Dist: isort >=5.13.2 ; extra == 'dev'
Requires-Dist: blue >=0.9.1 ; extra == 'dev'
Requires-Dist: mkdocstrings >=0.25.2 ; extra == 'doc'
Requires-Dist: mkdocstrings-python >=1.10.8 ; extra == 'doc'
Requires-Dist: mkdocs-macros-plugin >=1.0.5 ; extra == 'doc'
Requires-Dist: jinja2 >=3.1.4 ; extra == 'doc'
Requires-Dist: termynal >=0.12.1 ; extra == 'doc'
Requires-Dist: mkdocs-material >=9.5.32 ; extra == 'doc'
Provides-Extra: dev
Provides-Extra: doc
Summary: GRAMEP - Genome vaRiation Analysis from the Maximum Entropy Principle
Author-email: Matheus Pimenta <omatheuspimenta@outlook.com>, Fabricio Lopes <fabricio@utfpr.edu.br>
Maintainer-email: Matheus Pimenta <omatheuspimenta@outlook.com>
License: MIT License
Requires-Python: >=3.12
Project-URL: Code, https://github.com/omatheuspimenta/GRAMEP
Project-URL: Bug Tracker, https://github.com/omatheuspimenta/GRAMEP/issues
Project-URL: Documentation, https://gramep.readthedocs.io/en/latest/
